allure_reporter/__init__.py
allure_reporter/allure-results/9d95e6e7-9cf6-4ca5-91b4-9b69ce0971f8-result.json
allure_reporter/cli.py
allure_reporter-0.0.1.dist-info/LICENSE.md
allure_reporter-0.0.1.dist-info/METADATA
allure_reporter-0.0.1.dist-info/WHEEL
allure_reporter-0.0.1.dist-info/entry_points.txt
allure_reporter-0.0.1.dist-info/RECORD
